slackforms/__init__.py
slackforms/admin.py
slackforms/apps.py
slackforms/conf.py
slackforms/urls.py
slackforms/handlers/__init__.py
slackforms/handlers/form.py
slackforms/handlers/manual.py
slackforms/handlers/slash.py
slackforms/handlers/interactions/__init__.py
slackforms/handlers/interactions/action.py
slackforms/handlers/interactions/base.py
slackforms/handlers/interactions/message.py
slackforms/migrations/0001_initial.py
slackforms/migrations/0002_auto_20181203_1901.py
slackforms/migrations/0003_auto_20181204_1728.py
slackforms/migrations/0004_auto_20181204_1729.py
slackforms/migrations/0005_auto_20181204_1731.py
slackforms/migrations/0006_auto_20181204_1731.py
slackforms/migrations/0007_auto_20181205_1625.py
slackforms/migrations/0008_auto_20181206_1640.py
slackforms/migrations/0009_auto_20181213_1921.py
slackforms/migrations/0010_auto_20181213_1923.py
slackforms/migrations/0011_auto_20181213_1953.py
slackforms/migrations/0012_auto_20181213_1954.py
slackforms/migrations/0013_auto_20181213_2037.py
slackforms/migrations/__init__.py
slackforms/models/__init__.py
slackforms/models/endpoint.py
slackforms/models/form.py
slackforms/models/token.py
slackforms/utils/__init__.py
slackforms/utils/importers.py
slackforms/utils/is_float.py
slackforms/utils/schema_to_form.py
slackforms/utils/slack.py
slackforms/views/__init__.py
slackforms/views/callback.py
slackforms/views/home.py
slackforms/views/message.py
django_slack_forms-0.1.2.dist-info/LICENSE
django_slack_forms-0.1.2.dist-info/METADATA
django_slack_forms-0.1.2.dist-info/WHEEL
django_slack_forms-0.1.2.dist-info/top_level.txt
django_slack_forms-0.1.2.dist-info/RECORD
